<?xml version="1.0" encoding="utf-8"?>
<savedqueries xmlns:xsi="http://www.w3.org/2001/XMLSchema-instance">
  <savedquery>
    <IsCustomizable>1</IsCustomizable>
    <CanBeDeleted>0</CanBeDeleted>
    <isquickfindquery>0</isquickfindquery>
    <isprivate>0</isprivate>
    <isdefault>0</isdefault>
    <savedqueryid>{4834a790-a3e3-4612-8294-32e9a8b8d4bf}</savedqueryid>
    <layoutxml>
      <grid name="resultset" jump="cr664_covenantname" select="1" icon="1" preview="1">
        <row name="result" id="cr664_covenantid">
          <cell name="cr664_covenantname" width="300" />
          <cell name="createdon" width="125" />
        </row>
      </grid>
    </layoutxml>
    <querytype>0</querytype>
    <fetchxml>
      <fetch version="1.0" mapping="logical">
        <entity name="cr664_covenant">
          <attribute name="cr664_covenantid" />
          <attribute name="cr664_covenantname" />
          <attribute name="createdon" />
          <order attribute="cr664_covenantname" descending="false" />
          <filter type="and">
            <condition attribute="statecode" operator="eq" value="1" />
          </filter>
        </entity>
      </fetch>
    </fetchxml>
    <IntroducedVersion>1.0.0.0</IntroducedVersion>
    <LocalizedNames>
      <LocalizedName description="Inactive Covenants" languagecode="1033" />
    </LocalizedNames>
  </savedquery>
</savedqueries>